[{"ID":1,"Login":"user1","Password":"user","Name":"test","Birthdate":"2000-01-25T00:00:00","PhoneNo":"1232123","Books":null,"Email":"email@test.com","AuthorId":2},{"ID":1,"Login":"tinojnr","Password":"triddakid","Name":"tino","Birthdate":"2021-01-26T07:49:13.2927188+07:00","PhoneNo":"9880989809","Books":null,"Email":"tyututyuoi@tridakid9.com","AuthorId":0},{"ID":1,"Login":"nasty","Password":"nasssssty","Name":"nastya","Birthdate":"2021-01-26T08:31:05.3571138+07:00","PhoneNo":"9998787766","Books":null,"Email":"nastya@gmail.com","AuthorId":0},{"ID":809,"Login":"yiuidsa","Password":"uiuiad","Name":"iuoijoi","Birthdate":"2021-01-26T13:47:37.5249602+07:00","PhoneNo":"(893)-233-5910","Books":null,"Email":"tinojunior120@gmail.com","AuthorId":0}]